{
    "resourceType": "Questionnaire",
    "meta": {
        "profile": [
            "http://gtri.gatech.edu/fakeFormIg/StructureDefinition/smartchart-form"
        ]
    },
    "id": "",
    "url": "Questionnaire/",
    "name": "",
    "version": "",
    "title": "",
    "status": "draft",
    "experimental": true,
    "publisher": "GTRI",
    "description": "",
    "subjectType": [
        "Patient"
    ],
    "extension": [{
        "url": "http://gtri.gatech.edu/fakeFormIg/cql-form-job-list",
        "extension": [

        ]
    }, {
        "url": "http://gtri.gatech.edu/fakeFormIg/nlpql-form-job-list",
        "extension": [

        ]
    }],
    "item": []
}